LICENSE
MANIFEST.in
README.md
petl_ldap3.py
setup.py
petl_ldap3.egg-info/PKG-INFO
petl_ldap3.egg-info/SOURCES.txt
petl_ldap3.egg-info/dependency_links.txt
petl_ldap3.egg-info/requires.txt
petl_ldap3.egg-info/top_level.txt